prompt_vcs/__init__.py
prompt_vcs/ab_storage.py
prompt_vcs/ab_testing.py
prompt_vcs/api.py
prompt_vcs/cli.py
prompt_vcs/codemod.py
prompt_vcs/extractor.py
prompt_vcs/manager.py
prompt_vcs/templates.py
prompt_vcs/testing.py
prompt_vcs/validator.py
prompt_vcs-0.5.0.dist-info/METADATA
prompt_vcs-0.5.0.dist-info/WHEEL
prompt_vcs-0.5.0.dist-info/entry_points.txt
prompt_vcs-0.5.0.dist-info/licenses/LICENSE
prompt_vcs-0.5.0.dist-info/RECORD
