Metadata-Version: 2.4
Name: prompt-vcs
Version: 0.5.0
Summary: Git-native prompt management library for LLM applications
Project-URL: Homepage, https://github.com/Dreamer431/prompt-vcs
Project-URL: Repository, https://github.com/Dreamer431/prompt-vcs
Project-URL: Documentation, https://github.com/Dreamer431/prompt-vcs#readme
Project-URL: Issues, https://github.com/Dreamer431/prompt-vcs/issues
Author-email: emerard <denghaowen59@gmail.com>
Maintainer-email: emerard <denghaowen59@gmail.com>
License-Expression: MIT
License-File: LICENSE
Keywords: ai,chatgpt,git,langchain,llm,prompt,prompt-engineering,version-control
Classifier: Development Status :: 4 - Beta
Classifier: Intended Audience :: Developers
Classifier: License :: OSI Approved :: MIT License
Classifier: Operating System :: OS Independent
Classifier: Programming Language :: Python :: 3
Classifier: Programming Language :: Python :: 3.10
Classifier: Programming Language :: Python :: 3.11
Classifier: Programming Language :: Python :: 3.12
Classifier: Programming Language :: Python :: 3.13
Classifier: Topic :: Software Development :: Libraries :: Python Modules
Classifier: Topic :: Software Development :: Version Control :: Git
Classifier: Typing :: Typed
Requires-Python: >=3.10
Requires-Dist: jinja2>=3.1.0
Requires-Dist: libcst>=1.0.0
Requires-Dist: pyyaml>=6.0
Requires-Dist: typer[all]>=0.9.0
Provides-Extra: dev
Requires-Dist: pytest-cov>=4.0; extra == 'dev'
Requires-Dist: pytest>=7.0; extra == 'dev'
Provides-Extra: validation
Requires-Dist: jsonschema>=4.0; extra == 'validation'
